README.md
setup.py
agents/__init__.py
agents/algorithms/__init__.py
agents/algorithms/ppo/__init__.py
agents/algorithms/ppo/ppo.py
agents/algorithms/ppo/utility.py
agents/parts/__init__.py
agents/parts/iterate_sequences.py
agents/parts/memory.py
agents/parts/normalize.py
agents/scripts/__init__.py
agents/scripts/configs.py
agents/scripts/networks.py
agents/scripts/train.py
agents/scripts/train_ppo_test.py
agents/scripts/utility.py
agents/scripts/visualize.py
agents/tools/__init__.py
agents/tools/attr_dict.py
agents/tools/attr_dict_test.py
agents/tools/batch_env.py
agents/tools/count_weights.py
agents/tools/count_weights_test.py
agents/tools/in_graph_batch_env.py
agents/tools/in_graph_env.py
agents/tools/loop.py
agents/tools/loop_test.py
agents/tools/mock_algorithm.py
agents/tools/mock_environment.py
agents/tools/nested.py
agents/tools/nested_test.py
agents/tools/simulate.py
agents/tools/simulate_test.py
agents/tools/streaming_mean.py
agents/tools/wrappers.py
agents/tools/wrappers_test.py
batch_ppo.egg-info/PKG-INFO
batch_ppo.egg-info/SOURCES.txt
batch_ppo.egg-info/dependency_links.txt
batch_ppo.egg-info/requires.txt
batch_ppo.egg-info/top_level.txt