Metadata-Version: 1.1
Name: batch-ppo
Version: 1.4.0
Summary: Efficient TensorFlow implementation of reinforcement learning algorithms.
Home-page: http://github.com/google-research/batch-ppo
Author: UNKNOWN
Author-email: UNKNOWN
License: Apache 2.0
Platform: UNKNOWN
Classifier: Programming Language :: Python :: 2
Classifier: Programming Language :: Python :: 3
Classifier: License :: OSI Approved :: Apache Software License
Classifier: Topic :: Scientific/Engineering :: Artificial Intelligence
Classifier: Intended Audience :: Science/Research
